CHANGELOG.rst
LICENCE.rst
aleksis/apps/kort/__init__.py
aleksis/apps/kort/admin.py
aleksis/apps/kort/api.py
aleksis/apps/kort/apps.py
aleksis/apps/kort/forms.py
aleksis/apps/kort/frontend/index.js
aleksis/apps/kort/frontend/messages/de.json
aleksis/apps/kort/frontend/messages/en.json
aleksis/apps/kort/frontend/messages/ru.json
aleksis/apps/kort/frontend/messages/uk.json
aleksis/apps/kort/locale/.keepdir
aleksis/apps/kort/locale/ar/LC_MESSAGES/django.mo
aleksis/apps/kort/locale/ar/LC_MESSAGES/django.po
aleksis/apps/kort/locale/de_DE/LC_MESSAGES/django.mo
aleksis/apps/kort/locale/de_DE/LC_MESSAGES/django.po
aleksis/apps/kort/locale/fr/LC_MESSAGES/django.mo
aleksis/apps/kort/locale/fr/LC_MESSAGES/django.po
aleksis/apps/kort/locale/la/LC_MESSAGES/django.mo
aleksis/apps/kort/locale/la/LC_MESSAGES/django.po
aleksis/apps/kort/locale/nb_NO/LC_MESSAGES/django.mo
aleksis/apps/kort/locale/nb_NO/LC_MESSAGES/django.po
aleksis/apps/kort/locale/ru/LC_MESSAGES/django.mo
aleksis/apps/kort/locale/ru/LC_MESSAGES/django.po
aleksis/apps/kort/locale/tr_TR/LC_MESSAGES/django.mo
aleksis/apps/kort/locale/tr_TR/LC_MESSAGES/django.po
aleksis/apps/kort/locale/uk/LC_MESSAGES/django.mo
aleksis/apps/kort/locale/uk/LC_MESSAGES/django.po
aleksis/apps/kort/migrations/0001_initial.py
aleksis/apps/kort/migrations/0002_card_printer.py
aleksis/apps/kort/migrations/0003_auto_20220308_2023.py
aleksis/apps/kort/migrations/0004_alter_card_chip_number.py
aleksis/apps/kort/migrations/0005_card_pdf_file.py
aleksis/apps/kort/migrations/0006_auto_20220310_2003.py
aleksis/apps/kort/migrations/0007_auto_20220315_1957.py
aleksis/apps/kort/migrations/0008_auto_20220319_2018.py
aleksis/apps/kort/migrations/0009_cardprinter_generate_number_on_server.py
aleksis/apps/kort/migrations/0010_auto_20220326_2123.py
aleksis/apps/kort/migrations/0011_cardprinter_card_detector.py
aleksis/apps/kort/migrations/0012_auto_20220529_1435.py
aleksis/apps/kort/migrations/0013_auto_20220530_1939.py
aleksis_app_kort-0.4.dist-info/METADATA
aleksis_app_kort-0.4.dist-info/WHEEL
aleksis_app_kort-0.4.dist-info/entry_points.txt
aleksis_app_kort-0.4.dist-info/RECORD
