Metadata-Version: 2.1
Name: AlekSIS-App-Kort
Version: 0.4
Summary: AlekSIS (School Information System) — App Kort (manage student IDs)
Home-page: https://aleksis.org
License: EUPL-1.2-or-later
Author: Margarete Grassl
Author-email: grasslma@katharineum.de
Maintainer: Jonathan Weth
Maintainer-email: dev@jonathanweth.de
Requires-Python: >=3.9,<4.0
Classifier: Environment :: Web Environment
Classifier: Intended Audience :: Education
Classifier: License :: Other/Proprietary License
Classifier: Programming Language :: Python :: 3
Classifier: Programming Language :: Python :: 3.9
Classifier: Programming Language :: Python :: 3.10
Classifier: Programming Language :: Python :: 3.11
Classifier: Topic :: Education
Requires-Dist: aleksis-core (>=3.0,<4.0)
Requires-Dist: django-ace (>=1.0.12,<2.0.0)
Requires-Dist: django-formtools (>=2.3,<3.0)
Requires-Dist: python-barcode (>=0.15.0,<0.16.0)
Project-URL: Repository, https://edugit.org/AlekSIS/onboarding/AlekSIS-App-Kort
